{
  "schemaVersion": 1,
  "lock": "wallstop-organization-builds",
  "holder": null,
  "queue": [
    {
      "holderId": "Ambiguous-Interactive/unity-helpers:28263335388:unity-tests:2022.3.45f1-playmode",
      "repository": "Ambiguous-Interactive/unity-helpers",
      "workflow": "Unity Tests",
      "job": "unity-tests",
      "runId": "28263335388",
      "runAttempt": "1",
      "runUrl": "https://github.com/Ambiguous-Interactive/unity-helpers/actions/runs/28263335388",
      "queuedAt": "2026-06-26T21:44:29.055Z"
    }
  ],
  "updatedAt": "2026-06-26T21:44:59.459Z"
}
