{
  "schemaVersion": 1,
  "lock": "wallstop-organization-builds",
  "holder": {
    "holderId": "Ambiguous-Interactive/DxMessaging:28729538900:unity-tests:2022.3.45f1-editmode",
    "repository": "Ambiguous-Interactive/DxMessaging",
    "workflow": "Unity Tests",
    "job": "unity-tests",
    "runId": "28729538900",
    "runAttempt": "1",
    "runUrl": "https://github.com/Ambiguous-Interactive/DxMessaging/actions/runs/28729538900",
    "queuedAt": "2026-07-05T05:16:07.034Z",
    "acquiredAt": "2026-07-05T05:16:07.601Z",
    "expiresAt": "2026-07-05T09:16:07.601Z"
  },
  "queue": [],
  "updatedAt": "2026-07-05T05:16:07.601Z"
}
