{
  "schemaVersion": 5,
  "lock": "wallstop-organization-builds",
  "holder": {
    "holderId": "Ambiguous-Interactive/DxMessaging:29491677615:perf-benchmarks:perf-6000.3.16f1-playmode",
    "repository": "Ambiguous-Interactive/DxMessaging",
    "workflow": "Performance Numbers",
    "job": "perf-benchmarks",
    "runId": "29491677615",
    "runAttempt": "1",
    "runUrl": "https://github.com/Ambiguous-Interactive/DxMessaging/actions/runs/29491677615",
    "queuedAt": "2026-07-16T10:54:24.063Z",
    "acquiredAt": "2026-07-16T10:59:59.557Z",
    "expiresAt": "2026-07-16T14:59:59.557Z",
    "runnerId": "ELI-MACHINE"
  },
  "holders": [
    {
      "holderId": "Ambiguous-Interactive/DxMessaging:29491677615:perf-benchmarks:perf-6000.3.16f1-playmode",
      "repository": "Ambiguous-Interactive/DxMessaging",
      "workflow": "Performance Numbers",
      "job": "perf-benchmarks",
      "runId": "29491677615",
      "runAttempt": "1",
      "runUrl": "https://github.com/Ambiguous-Interactive/DxMessaging/actions/runs/29491677615",
      "queuedAt": "2026-07-16T10:54:24.063Z",
      "acquiredAt": "2026-07-16T10:59:59.557Z",
      "expiresAt": "2026-07-16T14:59:59.557Z",
      "runnerId": "ELI-MACHINE"
    }
  ],
  "queue": [
    {
      "holderId": "Ambiguous-Interactive/DxMessaging:29491677682:unity-tests:2022.3.45f1-editmode",
      "repository": "Ambiguous-Interactive/DxMessaging",
      "workflow": "Unity Tests",
      "job": "unity-tests",
      "runId": "29491677682",
      "runAttempt": "1",
      "runUrl": "https://github.com/Ambiguous-Interactive/DxMessaging/actions/runs/29491677682",
      "queuedAt": "2026-07-16T11:02:48.134Z",
      "runnerId": "DAD-MACHINE"
    }
  ],
  "reservations": [
    {
      "reservationId": "032f32d5-edc7-4892-80d9-63082821474d",
      "holderId": "Ambiguous-Interactive/DxMessaging:29491677682:unity-tests:2021.3.45f1-standalone",
      "repository": "Ambiguous-Interactive/DxMessaging",
      "workflow": "Unity Tests",
      "job": "unity-tests",
      "runId": "29491677682",
      "runAttempt": "1",
      "runUrl": "https://github.com/Ambiguous-Interactive/DxMessaging/actions/runs/29491677682",
      "runnerId": "DAD-MACHINE",
      "state": "cooldown",
      "reason": "cleanup-confirmed",
      "createdAt": "2026-07-16T11:01:24.020Z",
      "availableAt": "2026-07-16T11:07:24.020Z"
    }
  ],
  "activeIncident": null,
  "updatedAt": "2026-07-16T11:02:49.312Z"
}
