{
  "schemaVersion": 1,
  "lock": "wallstop-organization-builds",
  "holder": {
    "holderId": "Ambiguous-Interactive/unity-helpers:28712519322:unity-tests:6000.3.16f1-playmode",
    "repository": "Ambiguous-Interactive/unity-helpers",
    "workflow": "Unity Tests",
    "job": "unity-tests",
    "runId": "28712519322",
    "runAttempt": "1",
    "runUrl": "https://github.com/Ambiguous-Interactive/unity-helpers/actions/runs/28712519322",
    "queuedAt": "2026-07-04T17:21:27.096Z",
    "acquiredAt": "2026-07-04T17:28:05.919Z",
    "expiresAt": "2026-07-04T21:28:05.919Z"
  },
  "queue": [],
  "updatedAt": "2026-07-04T17:28:05.919Z"
}
