{
  "schemaVersion": 1,
  "lock": "wallstop-organization-builds",
  "holder": {
    "holderId": "Ambiguous-Interactive/DxMessaging:28715602264:unity-tests:2021.3.45f1-standalone",
    "repository": "Ambiguous-Interactive/DxMessaging",
    "workflow": "Unity Tests",
    "job": "unity-tests",
    "runId": "28715602264",
    "runAttempt": "1",
    "runUrl": "https://github.com/Ambiguous-Interactive/DxMessaging/actions/runs/28715602264",
    "queuedAt": "2026-07-04T18:44:11.395Z",
    "acquiredAt": "2026-07-04T18:44:11.935Z",
    "expiresAt": "2026-07-04T22:44:11.935Z"
  },
  "queue": [
    {
      "holderId": "Ambiguous-Interactive/DxMessaging:28715188748:unity-tests:2022.3.45f1-standalone",
      "repository": "Ambiguous-Interactive/DxMessaging",
      "workflow": "Unity Tests",
      "job": "unity-tests",
      "runId": "28715188748",
      "runAttempt": "1",
      "runUrl": "https://github.com/Ambiguous-Interactive/DxMessaging/actions/runs/28715188748",
      "queuedAt": "2026-07-04T18:45:06.505Z"
    }
  ],
  "updatedAt": "2026-07-04T18:45:07.381Z"
}
