{
  "schemaVersion": 5,
  "lock": "wallstop-organization-builds",
  "holder": {
    "holderId": "Ambiguous-Interactive/DoxReloaded:29774222512:build-webgl:build-webgl",
    "repository": "Ambiguous-Interactive/DoxReloaded",
    "workflow": "Build and Deploy",
    "job": "build-webgl",
    "runId": "29774222512",
    "runAttempt": "1",
    "runUrl": "https://github.com/Ambiguous-Interactive/DoxReloaded/actions/runs/29774222512",
    "queuedAt": "2026-07-20T20:08:01.180Z",
    "acquiredAt": "2026-07-20T20:08:03.894Z",
    "expiresAt": "2026-07-21T00:08:03.894Z",
    "runnerId": "tiny-box-linux"
  },
  "holders": [
    {
      "holderId": "Ambiguous-Interactive/DoxReloaded:29774222512:build-webgl:build-webgl",
      "repository": "Ambiguous-Interactive/DoxReloaded",
      "workflow": "Build and Deploy",
      "job": "build-webgl",
      "runId": "29774222512",
      "runAttempt": "1",
      "runUrl": "https://github.com/Ambiguous-Interactive/DoxReloaded/actions/runs/29774222512",
      "queuedAt": "2026-07-20T20:08:01.180Z",
      "acquiredAt": "2026-07-20T20:08:03.894Z",
      "expiresAt": "2026-07-21T00:08:03.894Z",
      "runnerId": "tiny-box-linux"
    }
  ],
  "queue": [],
  "reservations": [
    {
      "reservationId": "07ddd674-0be5-4d2b-9369-e49d2da83229",
      "holderId": "Ambiguous-Interactive/IshoBoy:29774507316:unity-compile-check:unity-ci-compile-check",
      "repository": "Ambiguous-Interactive/IshoBoy",
      "workflow": "Unity CI Validation",
      "job": "unity-compile-check",
      "runId": "29774507316",
      "runAttempt": "1",
      "runUrl": "https://github.com/Ambiguous-Interactive/IshoBoy/actions/runs/29774507316",
      "runnerId": "DAD-MACHINE",
      "state": "cooldown",
      "reason": "cleanup-confirmed",
      "createdAt": "2026-07-20T20:09:40.844Z",
      "availableAt": "2026-07-20T20:09:41.844Z"
    }
  ],
  "activeIncident": null,
  "updatedAt": "2026-07-20T20:09:40.844Z"
}
