{
  "schemaVersion": 5,
  "lock": "wallstop-organization-builds",
  "holder": null,
  "holders": [],
  "queue": [
    {
      "holderId": "Ambiguous-Interactive/unity-helpers:29379321713:unity-tests-single-threaded:6000.3.16f1-editmode-single-threaded",
      "repository": "Ambiguous-Interactive/unity-helpers",
      "workflow": "Unity Tests",
      "job": "unity-tests-single-threaded",
      "runId": "29379321713",
      "runAttempt": "1",
      "runUrl": "https://github.com/Ambiguous-Interactive/unity-helpers/actions/runs/29379321713",
      "queuedAt": "2026-07-15T04:03:22.838Z",
      "runnerId": "DAD-MACHINE"
    }
  ],
  "reservations": [
    {
      "reservationId": "7f802174-4295-452c-90a3-498570b73c78",
      "holderId": "Ambiguous-Interactive/unity-helpers:29379321713:unity-tests-single-threaded:6000.3.16f1-playmode-single-threaded",
      "repository": "Ambiguous-Interactive/unity-helpers",
      "workflow": "Unity Tests",
      "job": "unity-tests-single-threaded",
      "runId": "29379321713",
      "runAttempt": "1",
      "runUrl": "https://github.com/Ambiguous-Interactive/unity-helpers/actions/runs/29379321713",
      "runnerId": "DAD-MACHINE",
      "state": "cooldown",
      "reason": "cleanup-confirmed",
      "createdAt": "2026-07-15T04:02:39.697Z",
      "availableAt": "2026-07-15T04:08:39.697Z"
    }
  ],
  "activeIncident": null,
  "updatedAt": "2026-07-15T04:03:23.938Z"
}
