{
  "schemaVersion": 1,
  "lock": "wallstop-organization-builds",
  "holder": {
    "holderId": "Ambiguous-Interactive/DxMessaging:28349077275:unity-tests:2021.3.45f1-standalone",
    "repository": "Ambiguous-Interactive/DxMessaging",
    "workflow": "Unity Tests",
    "job": "unity-tests",
    "runId": "28349077275",
    "runAttempt": "1",
    "runUrl": "https://github.com/Ambiguous-Interactive/DxMessaging/actions/runs/28349077275",
    "queuedAt": "2026-06-29T04:51:08.532Z",
    "acquiredAt": "2026-06-29T04:55:58.792Z",
    "expiresAt": "2026-06-29T08:55:58.792Z"
  },
  "queue": [],
  "updatedAt": "2026-06-29T04:55:58.792Z"
}
