{
  "schemaVersion": 1,
  "lock": "wallstop-organization-builds",
  "holder": {
    "holderId": "Ambiguous-Interactive/unity-helpers:28761754283:unity-tests:2022.3.45f1-editmode",
    "repository": "Ambiguous-Interactive/unity-helpers",
    "workflow": "Unity Tests",
    "job": "unity-tests",
    "runId": "28761754283",
    "runAttempt": "1",
    "runUrl": "https://github.com/Ambiguous-Interactive/unity-helpers/actions/runs/28761754283",
    "queuedAt": "2026-07-06T01:19:39.728Z",
    "acquiredAt": "2026-07-06T01:19:40.300Z",
    "expiresAt": "2026-07-06T05:19:40.300Z"
  },
  "queue": [],
  "updatedAt": "2026-07-06T01:19:40.300Z"
}
