{
  "schemaVersion": 1,
  "lock": "wallstop-organization-builds",
  "holder": {
    "holderId": "Ambiguous-Interactive/DxMessaging:27454833110:unity-tests:6000.3.16f1-editmode",
    "repository": "Ambiguous-Interactive/DxMessaging",
    "workflow": "Unity Tests",
    "job": "unity-tests",
    "runId": "27454833110",
    "runAttempt": "1",
    "runUrl": "https://github.com/Ambiguous-Interactive/DxMessaging/actions/runs/27454833110",
    "queuedAt": "2026-06-13T03:43:58.678Z",
    "acquiredAt": "2026-06-13T03:44:35.530Z",
    "expiresAt": "2026-06-13T07:44:35.530Z"
  },
  "queue": [
    {
      "holderId": "Ambiguous-Interactive/DxMessaging:27455330345:unity-tests:2022.3.45f1-editmode",
      "repository": "Ambiguous-Interactive/DxMessaging",
      "workflow": "Unity Tests",
      "job": "unity-tests",
      "runId": "27455330345",
      "runAttempt": "1",
      "runUrl": "https://github.com/Ambiguous-Interactive/DxMessaging/actions/runs/27455330345",
      "queuedAt": "2026-06-13T03:44:58.563Z"
    }
  ],
  "updatedAt": "2026-06-13T03:44:59.464Z"
}
