{
  "schemaVersion": 5,
  "lock": "wallstop-organization-builds",
  "holder": {
    "holderId": "Ambiguous-Interactive/DxMessaging:29733706643:perf-benchmarks:perf-6000.3.16f1-standalone",
    "repository": "Ambiguous-Interactive/DxMessaging",
    "workflow": "Performance Numbers",
    "job": "perf-benchmarks",
    "runId": "29733706643",
    "runAttempt": "1",
    "runUrl": "https://github.com/Ambiguous-Interactive/DxMessaging/actions/runs/29733706643",
    "queuedAt": "2026-07-20T10:04:50.113Z",
    "acquiredAt": "2026-07-20T10:04:51.323Z",
    "expiresAt": "2026-07-20T14:04:51.323Z",
    "runnerId": "ELI-MACHINE"
  },
  "holders": [
    {
      "holderId": "Ambiguous-Interactive/DxMessaging:29733706643:perf-benchmarks:perf-6000.3.16f1-standalone",
      "repository": "Ambiguous-Interactive/DxMessaging",
      "workflow": "Performance Numbers",
      "job": "perf-benchmarks",
      "runId": "29733706643",
      "runAttempt": "1",
      "runUrl": "https://github.com/Ambiguous-Interactive/DxMessaging/actions/runs/29733706643",
      "queuedAt": "2026-07-20T10:04:50.113Z",
      "acquiredAt": "2026-07-20T10:04:51.323Z",
      "expiresAt": "2026-07-20T14:04:51.323Z",
      "runnerId": "ELI-MACHINE"
    },
    {
      "holderId": "Ambiguous-Interactive/unity-helpers:29731362266:unity-tests-single-threaded:6000.3.16f1-editmode-single-threaded",
      "repository": "Ambiguous-Interactive/unity-helpers",
      "workflow": "Unity Tests",
      "job": "unity-tests-single-threaded",
      "runId": "29731362266",
      "runAttempt": "1",
      "runUrl": "https://github.com/Ambiguous-Interactive/unity-helpers/actions/runs/29731362266",
      "queuedAt": "2026-07-20T10:15:42.545Z",
      "acquiredAt": "2026-07-20T10:15:43.905Z",
      "expiresAt": "2026-07-20T14:15:43.905Z",
      "runnerId": "DAD-MACHINE"
    }
  ],
  "queue": [],
  "reservations": [],
  "activeIncident": null,
  "updatedAt": "2026-07-20T10:15:43.905Z"
}
