{
  "schemaVersion": 5,
  "lock": "wallstop-organization-builds",
  "holder": null,
  "holders": [],
  "queue": [],
  "reservations": [
    {
      "reservationId": "bb17e6df-a413-4f75-a653-3369888be5ad",
      "holderId": "Ambiguous-Interactive/unity-helpers:29796316020:unity-tests:2022.3.45f1-playmode",
      "repository": "Ambiguous-Interactive/unity-helpers",
      "workflow": "Unity Tests",
      "job": "unity-tests",
      "runId": "29796316020",
      "runAttempt": "1",
      "runUrl": "https://github.com/Ambiguous-Interactive/unity-helpers/actions/runs/29796316020",
      "runnerId": "ELI-MACHINE",
      "state": "cooldown",
      "reason": "cleanup-confirmed",
      "createdAt": "2026-07-21T02:55:15.619Z",
      "availableAt": "2026-07-21T02:55:16.619Z"
    }
  ],
  "activeIncident": null,
  "updatedAt": "2026-07-21T02:55:15.619Z"
}
