{
  "schemaVersion": 1,
  "lock": "wallstop-organization-builds",
  "holder": null,
  "queue": [
    {
      "holderId": "Ambiguous-Interactive/DxMessaging:28273835749:unity-tests:2021.3.45f1-playmode",
      "repository": "Ambiguous-Interactive/DxMessaging",
      "workflow": "Unity Tests",
      "job": "unity-tests",
      "runId": "28273835749",
      "runAttempt": "1",
      "runUrl": "https://github.com/Ambiguous-Interactive/DxMessaging/actions/runs/28273835749",
      "queuedAt": "2026-06-27T01:09:38.421Z"
    }
  ],
  "updatedAt": "2026-06-27T01:11:13.405Z"
}
