{
  "schemaVersion": 1,
  "lock": "wallstop-organization-builds",
  "holder": {
    "holderId": "Ambiguous-Interactive/unity-helpers:28562333024:unity-tests:2022.3.45f1-playmode",
    "repository": "Ambiguous-Interactive/unity-helpers",
    "workflow": "Unity Tests",
    "job": "unity-tests",
    "runId": "28562333024",
    "runAttempt": "1",
    "runUrl": "https://github.com/Ambiguous-Interactive/unity-helpers/actions/runs/28562333024",
    "queuedAt": "2026-07-02T03:41:14.081Z",
    "acquiredAt": "2026-07-02T03:41:14.756Z",
    "expiresAt": "2026-07-02T07:41:14.756Z"
  },
  "queue": [],
  "updatedAt": "2026-07-02T03:41:14.756Z"
}
