{
  "schemaVersion": 5,
  "lock": "wallstop-organization-builds",
  "holder": null,
  "holders": [],
  "queue": [],
  "reservations": [
    {
      "reservationId": "afe73d12-fd1b-4103-9172-0ea37155b98d",
      "holderId": "Ambiguous-Interactive/DoxReloaded:30068051891:unity-tests:unity-tests-0",
      "repository": "Ambiguous-Interactive/DoxReloaded",
      "workflow": "Build and Deploy",
      "job": "unity-tests",
      "runId": "30068051891",
      "runAttempt": "1",
      "runUrl": "https://github.com/Ambiguous-Interactive/DoxReloaded/actions/runs/30068051891",
      "runnerId": "box-linux",
      "state": "cooldown",
      "reason": "cleanup-confirmed",
      "createdAt": "2026-07-24T05:05:00.986Z",
      "availableAt": "2026-07-24T05:05:01.986Z"
    }
  ],
  "activeIncident": null,
  "updatedAt": "2026-07-24T05:05:00.987Z"
}
