{
  "schemaVersion": 5,
  "lock": "wallstop-organization-builds",
  "holder": {
    "holderId": "Ambiguous-Interactive/DxMessaging:29525109940:unity-tests:6000.3.16f1-standalone",
    "repository": "Ambiguous-Interactive/DxMessaging",
    "workflow": "Unity Tests",
    "job": "unity-tests",
    "runId": "29525109940",
    "runAttempt": "1",
    "runUrl": "https://github.com/Ambiguous-Interactive/DxMessaging/actions/runs/29525109940",
    "queuedAt": "2026-07-16T20:28:18.755Z",
    "acquiredAt": "2026-07-16T20:33:29.073Z",
    "expiresAt": "2026-07-17T00:33:29.073Z",
    "runnerId": "ELI-MACHINE"
  },
  "holders": [
    {
      "holderId": "Ambiguous-Interactive/DxMessaging:29525109940:unity-tests:6000.3.16f1-standalone",
      "repository": "Ambiguous-Interactive/DxMessaging",
      "workflow": "Unity Tests",
      "job": "unity-tests",
      "runId": "29525109940",
      "runAttempt": "1",
      "runUrl": "https://github.com/Ambiguous-Interactive/DxMessaging/actions/runs/29525109940",
      "queuedAt": "2026-07-16T20:28:18.755Z",
      "acquiredAt": "2026-07-16T20:33:29.073Z",
      "expiresAt": "2026-07-17T00:33:29.073Z",
      "runnerId": "ELI-MACHINE"
    }
  ],
  "queue": [
    {
      "holderId": "Ambiguous-Interactive/DoxReloaded:29528797699:build-webgl:build-webgl",
      "repository": "Ambiguous-Interactive/DoxReloaded",
      "workflow": "Build and Deploy",
      "job": "build-webgl",
      "runId": "29528797699",
      "runAttempt": "1",
      "runUrl": "https://github.com/Ambiguous-Interactive/DoxReloaded/actions/runs/29528797699",
      "queuedAt": "2026-07-16T20:32:09.047Z",
      "runnerId": "box-linux"
    }
  ],
  "reservations": [
    {
      "reservationId": "d934fc60-7917-49b5-8388-9872cd24cc5e",
      "holderId": "Ambiguous-Interactive/DoxReloaded:29531009081:unity-tests:unity-tests-0",
      "repository": "Ambiguous-Interactive/DoxReloaded",
      "workflow": "Build and Deploy",
      "job": "unity-tests",
      "runId": "29531009081",
      "runAttempt": "1",
      "runUrl": "https://github.com/Ambiguous-Interactive/DoxReloaded/actions/runs/29531009081",
      "runnerId": "box-linux",
      "state": "cooldown",
      "reason": "cleanup-confirmed",
      "createdAt": "2026-07-16T20:30:39.888Z",
      "availableAt": "2026-07-16T20:36:39.888Z"
    }
  ],
  "activeIncident": null,
  "updatedAt": "2026-07-16T20:33:29.073Z"
}
