{
  "schemaVersion": 1,
  "lock": "wallstop-organization-builds",
  "holder": {
    "holderId": "Ambiguous-Interactive/DxMessaging:27519042152:unity-tests:2022.3.45f1-playmode",
    "repository": "Ambiguous-Interactive/DxMessaging",
    "workflow": "Unity Tests",
    "job": "unity-tests",
    "runId": "27519042152",
    "runAttempt": "1",
    "runUrl": "https://github.com/Ambiguous-Interactive/DxMessaging/actions/runs/27519042152",
    "queuedAt": "2026-06-15T02:02:24.598Z",
    "acquiredAt": "2026-06-15T02:02:45.589Z",
    "expiresAt": "2026-06-15T06:02:45.589Z"
  },
  "queue": [
    {
      "holderId": "Ambiguous-Interactive/DxMessaging:27519590363:unity-tests:2021.3.45f1-playmode",
      "repository": "Ambiguous-Interactive/DxMessaging",
      "workflow": "Unity Tests",
      "job": "unity-tests",
      "runId": "27519590363",
      "runAttempt": "1",
      "runUrl": "https://github.com/Ambiguous-Interactive/DxMessaging/actions/runs/27519590363",
      "queuedAt": "2026-06-15T02:02:58.136Z"
    }
  ],
  "updatedAt": "2026-06-15T02:02:59.012Z"
}
