{
  "schemaVersion": 1,
  "lock": "wallstop-organization-builds",
  "holder": {
    "holderId": "Ambiguous-Interactive/DxMessaging:28265148651:unity-tests:2021.3.45f1-playmode",
    "repository": "Ambiguous-Interactive/DxMessaging",
    "workflow": "Unity Tests",
    "job": "unity-tests",
    "runId": "28265148651",
    "runAttempt": "1",
    "runUrl": "https://github.com/Ambiguous-Interactive/DxMessaging/actions/runs/28265148651",
    "queuedAt": "2026-06-26T21:32:01.363Z",
    "acquiredAt": "2026-06-26T21:33:50.566Z",
    "expiresAt": "2026-06-27T01:33:50.566Z"
  },
  "queue": [],
  "updatedAt": "2026-06-26T21:33:50.566Z"
}
