{
  "schemaVersion": 5,
  "lock": "wallstop-organization-builds",
  "holder": null,
  "holders": [],
  "queue": [
    {
      "holderId": "Ambiguous-Interactive/DepartmentOfArrangements:29461649247:unity-tests:unity-ci-PlayMode",
      "repository": "Ambiguous-Interactive/DepartmentOfArrangements",
      "workflow": "Unity CI Validation",
      "job": "unity-tests",
      "runId": "29461649247",
      "runAttempt": "1",
      "runUrl": "https://github.com/Ambiguous-Interactive/DepartmentOfArrangements/actions/runs/29461649247",
      "queuedAt": "2026-07-16T00:43:05.388Z",
      "runnerId": "box-linux"
    },
    {
      "holderId": "Ambiguous-Interactive/DxMessaging:29458003885:perf-benchmarks:perf-6000.3.16f1-playmode",
      "repository": "Ambiguous-Interactive/DxMessaging",
      "workflow": "Performance Numbers",
      "job": "perf-benchmarks",
      "runId": "29458003885",
      "runAttempt": "1",
      "runUrl": "https://github.com/Ambiguous-Interactive/DxMessaging/actions/runs/29458003885",
      "queuedAt": "2026-07-16T00:48:40.493Z",
      "runnerId": "ELI-MACHINE"
    }
  ],
  "reservations": [
    {
      "reservationId": "512eba8b-dd3d-4152-8147-1ad59de09d7b",
      "holderId": "Ambiguous-Interactive/DxMessaging:29458003885:perf-benchmarks:perf-6000.3.16f1-standalone",
      "repository": "Ambiguous-Interactive/DxMessaging",
      "workflow": "Performance Numbers",
      "job": "perf-benchmarks",
      "runId": "29458003885",
      "runAttempt": "1",
      "runUrl": "https://github.com/Ambiguous-Interactive/DxMessaging/actions/runs/29458003885",
      "runnerId": "ELI-MACHINE",
      "state": "cooldown",
      "reason": "cleanup-confirmed",
      "createdAt": "2026-07-16T00:48:09.836Z",
      "availableAt": "2026-07-16T00:54:09.836Z"
    },
    {
      "reservationId": "e4b36b3b-d0dd-4bbf-8627-aaa34b1e25b4",
      "holderId": "Ambiguous-Interactive/DxMessaging:29458003753:unity-tests:2022.3.45f1-standalone",
      "repository": "Ambiguous-Interactive/DxMessaging",
      "workflow": "Unity Tests",
      "job": "unity-tests",
      "runId": "29458003753",
      "runAttempt": "1",
      "runUrl": "https://github.com/Ambiguous-Interactive/DxMessaging/actions/runs/29458003753",
      "runnerId": "DAD-MACHINE",
      "state": "cooldown",
      "reason": "cleanup-confirmed",
      "createdAt": "2026-07-16T00:49:19.152Z",
      "availableAt": "2026-07-16T00:55:19.152Z"
    }
  ],
  "activeIncident": null,
  "updatedAt": "2026-07-16T00:49:19.153Z"
}
