{
  "schemaVersion": 1,
  "lock": "wallstop-organization-builds",
  "holder": null,
  "queue": [
    {
      "holderId": "Ambiguous-Interactive/unity-helpers:28306108910:unity-tests:2022.3.45f1-editmode",
      "repository": "Ambiguous-Interactive/unity-helpers",
      "workflow": "Unity Tests",
      "job": "unity-tests",
      "runId": "28306108910",
      "runAttempt": "1",
      "runUrl": "https://github.com/Ambiguous-Interactive/unity-helpers/actions/runs/28306108910",
      "queuedAt": "2026-06-28T00:34:37.382Z"
    }
  ],
  "updatedAt": "2026-06-28T00:34:42.374Z"
}
