{
  "schemaVersion": 5,
  "lock": "wallstop-organization-builds",
  "holder": {
    "holderId": "Ambiguous-Interactive/unity-helpers:29386555287:unity-tests-standalone:2022.3.45f1-standalone",
    "repository": "Ambiguous-Interactive/unity-helpers",
    "workflow": "Unity Tests",
    "job": "unity-tests-standalone",
    "runId": "29386555287",
    "runAttempt": "1",
    "runUrl": "https://github.com/Ambiguous-Interactive/unity-helpers/actions/runs/29386555287",
    "queuedAt": "2026-07-15T06:24:04.402Z",
    "acquiredAt": "2026-07-15T06:29:02.807Z",
    "expiresAt": "2026-07-15T10:29:02.807Z",
    "runnerId": "ELI-MACHINE"
  },
  "holders": [
    {
      "holderId": "Ambiguous-Interactive/unity-helpers:29386555287:unity-tests-standalone:2022.3.45f1-standalone",
      "repository": "Ambiguous-Interactive/unity-helpers",
      "workflow": "Unity Tests",
      "job": "unity-tests-standalone",
      "runId": "29386555287",
      "runAttempt": "1",
      "runUrl": "https://github.com/Ambiguous-Interactive/unity-helpers/actions/runs/29386555287",
      "queuedAt": "2026-07-15T06:24:04.402Z",
      "acquiredAt": "2026-07-15T06:29:02.807Z",
      "expiresAt": "2026-07-15T10:29:02.807Z",
      "runnerId": "ELI-MACHINE"
    }
  ],
  "queue": [
    {
      "holderId": "Ambiguous-Interactive/unity-helpers:29386555287:unity-tests-standalone:6000.3.16f1-standalone",
      "repository": "Ambiguous-Interactive/unity-helpers",
      "workflow": "Unity Tests",
      "job": "unity-tests-standalone",
      "runId": "29386555287",
      "runAttempt": "1",
      "runUrl": "https://github.com/Ambiguous-Interactive/unity-helpers/actions/runs/29386555287",
      "queuedAt": "2026-07-15T06:41:33.537Z",
      "runnerId": "ELI-MACHINE"
    },
    {
      "holderId": "Ambiguous-Interactive/unity-helpers:29386555287:unity-tests-standalone:6000.5.2f1-standalone",
      "repository": "Ambiguous-Interactive/unity-helpers",
      "workflow": "Unity Tests",
      "job": "unity-tests-standalone",
      "runId": "29386555287",
      "runAttempt": "1",
      "runUrl": "https://github.com/Ambiguous-Interactive/unity-helpers/actions/runs/29386555287",
      "queuedAt": "2026-07-15T06:43:50.973Z",
      "runnerId": "DAD-MACHINE"
    }
  ],
  "reservations": [
    {
      "reservationId": "b6c2c260-4267-4ee7-897c-a9ccd1281028",
      "holderId": "Ambiguous-Interactive/qora-redux:29391664706:unity:qora-PlayMode",
      "repository": "Ambiguous-Interactive/qora-redux",
      "workflow": "Unity Tests",
      "job": "unity",
      "runId": "29391664706",
      "runAttempt": "1",
      "runUrl": "https://github.com/Ambiguous-Interactive/qora-redux/actions/runs/29391664706",
      "runnerId": "DAD-MACHINE",
      "state": "cooldown",
      "reason": "cleanup-confirmed",
      "createdAt": "2026-07-15T06:41:55.151Z",
      "availableAt": "2026-07-15T06:47:55.151Z"
    }
  ],
  "activeIncident": null,
  "updatedAt": "2026-07-15T06:43:52.160Z"
}
