{
  "schemaVersion": 5,
  "lock": "wallstop-organization-builds",
  "holder": {
    "holderId": "Ambiguous-Interactive/qora-redux:30052735236:unity:qora-PlayMode",
    "repository": "Ambiguous-Interactive/qora-redux",
    "workflow": "Unity Tests",
    "job": "unity",
    "runId": "30052735236",
    "runAttempt": "1",
    "runUrl": "https://github.com/Ambiguous-Interactive/qora-redux/actions/runs/30052735236",
    "queuedAt": "2026-07-23T23:18:19.297Z",
    "acquiredAt": "2026-07-23T23:18:22.033Z",
    "expiresAt": "2026-07-24T03:18:22.033Z",
    "runnerId": "ELI-MACHINE"
  },
  "holders": [
    {
      "holderId": "Ambiguous-Interactive/qora-redux:30052735236:unity:qora-PlayMode",
      "repository": "Ambiguous-Interactive/qora-redux",
      "workflow": "Unity Tests",
      "job": "unity",
      "runId": "30052735236",
      "runAttempt": "1",
      "runUrl": "https://github.com/Ambiguous-Interactive/qora-redux/actions/runs/30052735236",
      "queuedAt": "2026-07-23T23:18:19.297Z",
      "acquiredAt": "2026-07-23T23:18:22.033Z",
      "expiresAt": "2026-07-24T03:18:22.033Z",
      "runnerId": "ELI-MACHINE"
    },
    {
      "holderId": "Ambiguous-Interactive/qora-redux:30052735236:unity:qora-EditMode",
      "repository": "Ambiguous-Interactive/qora-redux",
      "workflow": "Unity Tests",
      "job": "unity",
      "runId": "30052735236",
      "runAttempt": "1",
      "runUrl": "https://github.com/Ambiguous-Interactive/qora-redux/actions/runs/30052735236",
      "queuedAt": "2026-07-23T23:18:18.668Z",
      "acquiredAt": "2026-07-23T23:18:21.384Z",
      "expiresAt": "2026-07-24T03:18:21.384Z",
      "runnerId": "DAD-MACHINE"
    }
  ],
  "queue": [],
  "reservations": [],
  "activeIncident": null,
  "updatedAt": "2026-07-23T23:18:21.385Z"
}
