{
  "schemaVersion": 1,
  "lock": "wallstop-organization-builds",
  "holder": {
    "holderId": "Ambiguous-Interactive/DxMessaging:27799266471:unity-tests:6000.3.16f1-playmode",
    "repository": "Ambiguous-Interactive/DxMessaging",
    "workflow": "Unity Tests",
    "job": "unity-tests",
    "runId": "27799266471",
    "runAttempt": "1",
    "runUrl": "https://github.com/Ambiguous-Interactive/DxMessaging/actions/runs/27799266471",
    "queuedAt": "2026-06-19T01:33:35.780Z",
    "acquiredAt": "2026-06-19T01:33:36.316Z",
    "expiresAt": "2026-06-19T05:33:36.316Z"
  },
  "queue": [],
  "updatedAt": "2026-06-19T01:33:36.316Z"
}
