{
  "schemaVersion": 5,
  "lock": "wallstop-organization-builds",
  "holder": {
    "holderId": "Ambiguous-Interactive/unity-helpers:29386555287:unity-tests-standalone:2022.3.45f1-standalone",
    "repository": "Ambiguous-Interactive/unity-helpers",
    "workflow": "Unity Tests",
    "job": "unity-tests-standalone",
    "runId": "29386555287",
    "runAttempt": "1",
    "runUrl": "https://github.com/Ambiguous-Interactive/unity-helpers/actions/runs/29386555287",
    "queuedAt": "2026-07-15T06:24:04.402Z",
    "acquiredAt": "2026-07-15T06:29:02.807Z",
    "expiresAt": "2026-07-15T10:29:02.807Z",
    "runnerId": "ELI-MACHINE"
  },
  "holders": [
    {
      "holderId": "Ambiguous-Interactive/unity-helpers:29386555287:unity-tests-standalone:2022.3.45f1-standalone",
      "repository": "Ambiguous-Interactive/unity-helpers",
      "workflow": "Unity Tests",
      "job": "unity-tests-standalone",
      "runId": "29386555287",
      "runAttempt": "1",
      "runUrl": "https://github.com/Ambiguous-Interactive/unity-helpers/actions/runs/29386555287",
      "queuedAt": "2026-07-15T06:24:04.402Z",
      "acquiredAt": "2026-07-15T06:29:02.807Z",
      "expiresAt": "2026-07-15T10:29:02.807Z",
      "runnerId": "ELI-MACHINE"
    }
  ],
  "queue": [],
  "reservations": [],
  "activeIncident": null,
  "updatedAt": "2026-07-15T06:29:02.807Z"
}
