{
  "schemaVersion": 5,
  "lock": "wallstop-organization-builds",
  "holder": {
    "holderId": "Ambiguous-Interactive/DxMessaging:29493584708:unity-tests:6000.3.16f1-editmode",
    "repository": "Ambiguous-Interactive/DxMessaging",
    "workflow": "Unity Tests",
    "job": "unity-tests",
    "runId": "29493584708",
    "runAttempt": "1",
    "runUrl": "https://github.com/Ambiguous-Interactive/DxMessaging/actions/runs/29493584708",
    "queuedAt": "2026-07-16T11:51:34.165Z",
    "acquiredAt": "2026-07-16T11:57:11.591Z",
    "expiresAt": "2026-07-16T15:57:11.591Z",
    "runnerId": "DAD-MACHINE"
  },
  "holders": [
    {
      "holderId": "Ambiguous-Interactive/DxMessaging:29493584708:unity-tests:6000.3.16f1-editmode",
      "repository": "Ambiguous-Interactive/DxMessaging",
      "workflow": "Unity Tests",
      "job": "unity-tests",
      "runId": "29493584708",
      "runAttempt": "1",
      "runUrl": "https://github.com/Ambiguous-Interactive/DxMessaging/actions/runs/29493584708",
      "queuedAt": "2026-07-16T11:51:34.165Z",
      "acquiredAt": "2026-07-16T11:57:11.591Z",
      "expiresAt": "2026-07-16T15:57:11.591Z",
      "runnerId": "DAD-MACHINE"
    }
  ],
  "queue": [],
  "reservations": [],
  "activeIncident": null,
  "updatedAt": "2026-07-16T11:57:11.591Z"
}
