{
  "schemaVersion": 5,
  "lock": "wallstop-organization-builds",
  "holder": {
    "holderId": "Ambiguous-Interactive/unity-helpers:29629898845:unity-tests:2022.3.45f1-editmode",
    "repository": "Ambiguous-Interactive/unity-helpers",
    "workflow": "Unity Tests",
    "job": "unity-tests",
    "runId": "29629898845",
    "runAttempt": "1",
    "runUrl": "https://github.com/Ambiguous-Interactive/unity-helpers/actions/runs/29629898845",
    "queuedAt": "2026-07-18T05:17:35.714Z",
    "acquiredAt": "2026-07-18T06:04:55.029Z",
    "expiresAt": "2026-07-18T10:04:55.029Z",
    "runnerId": "ELI-MACHINE"
  },
  "holders": [
    {
      "holderId": "Ambiguous-Interactive/unity-helpers:29629898845:unity-tests:2022.3.45f1-editmode",
      "repository": "Ambiguous-Interactive/unity-helpers",
      "workflow": "Unity Tests",
      "job": "unity-tests",
      "runId": "29629898845",
      "runAttempt": "1",
      "runUrl": "https://github.com/Ambiguous-Interactive/unity-helpers/actions/runs/29629898845",
      "queuedAt": "2026-07-18T05:17:35.714Z",
      "acquiredAt": "2026-07-18T06:04:55.029Z",
      "expiresAt": "2026-07-18T10:04:55.029Z",
      "runnerId": "ELI-MACHINE"
    }
  ],
  "queue": [
    {
      "holderId": "Ambiguous-Interactive/DoxReloaded:29631452538:build-webgl:build-webgl",
      "repository": "Ambiguous-Interactive/DoxReloaded",
      "workflow": "Build and Deploy",
      "job": "build-webgl",
      "runId": "29631452538",
      "runAttempt": "1",
      "runUrl": "https://github.com/Ambiguous-Interactive/DoxReloaded/actions/runs/29631452538",
      "queuedAt": "2026-07-18T05:38:35.721Z",
      "runnerId": "box-linux"
    },
    {
      "holderId": "Ambiguous-Interactive/IshoBoy:29631960315:unity-compile-check:unity-ci-compile-check",
      "repository": "Ambiguous-Interactive/IshoBoy",
      "workflow": "Unity CI Validation",
      "job": "unity-compile-check",
      "runId": "29631960315",
      "runAttempt": "1",
      "runUrl": "https://github.com/Ambiguous-Interactive/IshoBoy/actions/runs/29631960315",
      "queuedAt": "2026-07-18T06:03:53.081Z",
      "runnerId": "DAD-MACHINE"
    }
  ],
  "reservations": [
    {
      "reservationId": "32aee8cc-071b-43b8-bf25-48463f294ea0",
      "holderId": "Ambiguous-Interactive/unity-helpers:29600000212:unitypackage-smoke:unitypackage-smoke-29600000212",
      "repository": "Ambiguous-Interactive/unity-helpers",
      "workflow": "Unity Tests",
      "job": "unitypackage-smoke",
      "runId": "29600000212",
      "runAttempt": "1",
      "runUrl": "https://github.com/Ambiguous-Interactive/unity-helpers/actions/runs/29600000212",
      "runnerId": "GitHub Actions 1000111524",
      "state": "quarantine",
      "reason": "return-missing-positive-evidence",
      "createdAt": "2026-07-17T19:03:14.795Z"
    }
  ],
  "activeIncident": null,
  "updatedAt": "2026-07-18T06:04:55.029Z"
}
