{
  "schemaVersion": 1,
  "lock": "wallstop-organization-builds",
  "holder": {
    "holderId": "Ambiguous-Interactive/unity-helpers:28715690344:unitypackage:release-3.4.0",
    "repository": "Ambiguous-Interactive/unity-helpers",
    "workflow": "Release Publish",
    "job": "unitypackage",
    "runId": "28715690344",
    "runAttempt": "1",
    "runUrl": "https://github.com/Ambiguous-Interactive/unity-helpers/actions/runs/28715690344",
    "queuedAt": "2026-07-04T18:32:41.312Z",
    "acquiredAt": "2026-07-04T18:34:29.479Z",
    "expiresAt": "2026-07-04T22:34:29.479Z"
  },
  "queue": [],
  "updatedAt": "2026-07-04T18:34:29.480Z"
}
