{
  "schemaVersion": 5,
  "lock": "wallstop-organization-builds",
  "holder": null,
  "holders": [],
  "queue": [],
  "reservations": [
    {
      "reservationId": "7021448e-1ff5-488b-96f7-a048323df6c8",
      "holderId": "Ambiguous-Interactive/DxMessaging:29455563977:unity-tests:2021.3.45f1-standalone",
      "repository": "Ambiguous-Interactive/DxMessaging",
      "workflow": "Unity Tests",
      "job": "unity-tests",
      "runId": "29455563977",
      "runAttempt": "1",
      "runUrl": "https://github.com/Ambiguous-Interactive/DxMessaging/actions/runs/29455563977",
      "runnerId": "ELI-MACHINE",
      "state": "cooldown",
      "reason": "cleanup-confirmed",
      "createdAt": "2026-07-15T22:47:02.857Z",
      "availableAt": "2026-07-15T22:53:02.857Z"
    }
  ],
  "activeIncident": null,
  "updatedAt": "2026-07-15T22:47:02.857Z"
}
