{
  "schemaVersion": 5,
  "lock": "wallstop-organization-builds",
  "holder": null,
  "holders": [],
  "queue": [
    {
      "holderId": "Ambiguous-Interactive/DxMessaging:29493584708:unity-tests:2022.3.45f1-editmode",
      "repository": "Ambiguous-Interactive/DxMessaging",
      "workflow": "Unity Tests",
      "job": "unity-tests",
      "runId": "29493584708",
      "runAttempt": "1",
      "runUrl": "https://github.com/Ambiguous-Interactive/DxMessaging/actions/runs/29493584708",
      "queuedAt": "2026-07-16T11:33:34.342Z",
      "runnerId": "ELI-MACHINE"
    },
    {
      "holderId": "Ambiguous-Interactive/DxMessaging:29491677682:unity-tests:6000.3.16f1-standalone",
      "repository": "Ambiguous-Interactive/DxMessaging",
      "workflow": "Unity Tests",
      "job": "unity-tests",
      "runId": "29491677682",
      "runAttempt": "1",
      "runUrl": "https://github.com/Ambiguous-Interactive/DxMessaging/actions/runs/29491677682",
      "queuedAt": "2026-07-16T11:36:59.329Z",
      "runnerId": "DAD-MACHINE"
    }
  ],
  "reservations": [
    {
      "reservationId": "79197b4d-7774-4dea-a353-1c787419994d",
      "holderId": "Ambiguous-Interactive/DxMessaging:29493584708:unity-tests:2021.3.45f1-standalone",
      "repository": "Ambiguous-Interactive/DxMessaging",
      "workflow": "Unity Tests",
      "job": "unity-tests",
      "runId": "29493584708",
      "runAttempt": "1",
      "runUrl": "https://github.com/Ambiguous-Interactive/DxMessaging/actions/runs/29493584708",
      "runnerId": "ELI-MACHINE",
      "state": "cooldown",
      "reason": "cleanup-confirmed",
      "createdAt": "2026-07-16T11:33:04.884Z",
      "availableAt": "2026-07-16T11:39:04.884Z"
    },
    {
      "reservationId": "7345cf4c-90ce-4524-b062-619ceb8986d5",
      "holderId": "Ambiguous-Interactive/DxMessaging:29491677682:unity-tests:6000.3.16f1-playmode",
      "repository": "Ambiguous-Interactive/DxMessaging",
      "workflow": "Unity Tests",
      "job": "unity-tests",
      "runId": "29491677682",
      "runAttempt": "1",
      "runUrl": "https://github.com/Ambiguous-Interactive/DxMessaging/actions/runs/29491677682",
      "runnerId": "DAD-MACHINE",
      "state": "cooldown",
      "reason": "cleanup-confirmed",
      "createdAt": "2026-07-16T11:36:12.870Z",
      "availableAt": "2026-07-16T11:42:12.870Z"
    }
  ],
  "activeIncident": null,
  "updatedAt": "2026-07-16T11:37:00.654Z"
}
