{
  "schemaVersion": 5,
  "lock": "wallstop-organization-builds",
  "holder": {
    "holderId": "Ambiguous-Interactive/unity-helpers:29600000212:unity-tests:6000.5.2f1-editmode",
    "repository": "Ambiguous-Interactive/unity-helpers",
    "workflow": "Unity Tests",
    "job": "unity-tests",
    "runId": "29600000212",
    "runAttempt": "1",
    "runUrl": "https://github.com/Ambiguous-Interactive/unity-helpers/actions/runs/29600000212",
    "queuedAt": "2026-07-17T17:51:55.165Z",
    "acquiredAt": "2026-07-17T17:57:23.942Z",
    "expiresAt": "2026-07-17T21:57:23.942Z",
    "runnerId": "DAD-MACHINE"
  },
  "holders": [
    {
      "holderId": "Ambiguous-Interactive/unity-helpers:29600000212:unity-tests:6000.5.2f1-editmode",
      "repository": "Ambiguous-Interactive/unity-helpers",
      "workflow": "Unity Tests",
      "job": "unity-tests",
      "runId": "29600000212",
      "runAttempt": "1",
      "runUrl": "https://github.com/Ambiguous-Interactive/unity-helpers/actions/runs/29600000212",
      "queuedAt": "2026-07-17T17:51:55.165Z",
      "acquiredAt": "2026-07-17T17:57:23.942Z",
      "expiresAt": "2026-07-17T21:57:23.942Z",
      "runnerId": "DAD-MACHINE"
    }
  ],
  "queue": [
    {
      "holderId": "Ambiguous-Interactive/DxMessaging:29576997021:unity-tests:6000.3.16f1-playmode",
      "repository": "Ambiguous-Interactive/DxMessaging",
      "workflow": "Unity Tests",
      "job": "unity-tests",
      "runId": "29576997021",
      "runAttempt": "1",
      "runUrl": "https://github.com/Ambiguous-Interactive/DxMessaging/actions/runs/29576997021",
      "queuedAt": "2026-07-17T17:53:24.476Z",
      "runnerId": "ELI-MACHINE"
    }
  ],
  "reservations": [
    {
      "reservationId": "f06bc264-4b98-465f-ae0f-f466812b859e",
      "holderId": "Ambiguous-Interactive/unity-helpers:29600000212:unity-tests:6000.3.16f1-editmode",
      "repository": "Ambiguous-Interactive/unity-helpers",
      "workflow": "Unity Tests",
      "job": "unity-tests",
      "runId": "29600000212",
      "runAttempt": "1",
      "runUrl": "https://github.com/Ambiguous-Interactive/unity-helpers/actions/runs/29600000212",
      "runnerId": "ELI-MACHINE",
      "state": "cooldown",
      "reason": "cleanup-confirmed",
      "createdAt": "2026-07-17T17:52:53.422Z",
      "availableAt": "2026-07-17T17:58:53.422Z"
    }
  ],
  "activeIncident": null,
  "updatedAt": "2026-07-17T17:57:23.942Z"
}
