{
  "schemaVersion": 5,
  "lock": "wallstop-organization-builds",
  "holder": {
    "holderId": "Ambiguous-Interactive/DoxReloaded:29770775280:unity-tests:unity-tests-0",
    "repository": "Ambiguous-Interactive/DoxReloaded",
    "workflow": "Build and Deploy",
    "job": "unity-tests",
    "runId": "29770775280",
    "runAttempt": "1",
    "runUrl": "https://github.com/Ambiguous-Interactive/DoxReloaded/actions/runs/29770775280",
    "queuedAt": "2026-07-20T19:10:44.872Z",
    "acquiredAt": "2026-07-20T19:10:47.708Z",
    "expiresAt": "2026-07-20T23:10:47.708Z",
    "runnerId": "tiny-box-linux"
  },
  "holders": [
    {
      "holderId": "Ambiguous-Interactive/DoxReloaded:29770775280:unity-tests:unity-tests-0",
      "repository": "Ambiguous-Interactive/DoxReloaded",
      "workflow": "Build and Deploy",
      "job": "unity-tests",
      "runId": "29770775280",
      "runAttempt": "1",
      "runUrl": "https://github.com/Ambiguous-Interactive/DoxReloaded/actions/runs/29770775280",
      "queuedAt": "2026-07-20T19:10:44.872Z",
      "acquiredAt": "2026-07-20T19:10:47.708Z",
      "expiresAt": "2026-07-20T23:10:47.708Z",
      "runnerId": "tiny-box-linux"
    }
  ],
  "queue": [],
  "reservations": [
    {
      "reservationId": "ea2eb0b7-5b0b-4cc5-af7b-906b31de4db4",
      "holderId": "Ambiguous-Interactive/DoxReloaded:29770775280:unity-tests:unity-tests-1",
      "repository": "Ambiguous-Interactive/DoxReloaded",
      "workflow": "Build and Deploy",
      "job": "unity-tests",
      "runId": "29770775280",
      "runAttempt": "1",
      "runUrl": "https://github.com/Ambiguous-Interactive/DoxReloaded/actions/runs/29770775280",
      "runnerId": "box-linux",
      "state": "cooldown",
      "reason": "cleanup-confirmed",
      "createdAt": "2026-07-20T19:15:21.052Z",
      "availableAt": "2026-07-20T19:15:22.052Z"
    }
  ],
  "activeIncident": null,
  "updatedAt": "2026-07-20T19:15:21.054Z"
}
