{
  "schemaVersion": 3,
  "lock": "wallstop-organization-builds",
  "holder": {
    "holderId": "Ambiguous-Interactive/unity-helpers:29184066434:unity-tests:2022.3.45f1-editmode",
    "repository": "Ambiguous-Interactive/unity-helpers",
    "workflow": "Unity Tests",
    "job": "unity-tests",
    "runId": "29184066434",
    "runAttempt": "1",
    "runUrl": "https://github.com/Ambiguous-Interactive/unity-helpers/actions/runs/29184066434",
    "queuedAt": "2026-07-12T07:20:54.964Z",
    "acquiredAt": "2026-07-12T07:20:58.152Z",
    "expiresAt": "2026-07-12T11:20:58.152Z",
    "runnerId": "ELI-MACHINE"
  },
  "holders": [
    {
      "holderId": "Ambiguous-Interactive/unity-helpers:29184066434:unity-tests:2022.3.45f1-editmode",
      "repository": "Ambiguous-Interactive/unity-helpers",
      "workflow": "Unity Tests",
      "job": "unity-tests",
      "runId": "29184066434",
      "runAttempt": "1",
      "runUrl": "https://github.com/Ambiguous-Interactive/unity-helpers/actions/runs/29184066434",
      "queuedAt": "2026-07-12T07:20:54.964Z",
      "acquiredAt": "2026-07-12T07:20:58.152Z",
      "expiresAt": "2026-07-12T11:20:58.152Z",
      "runnerId": "ELI-MACHINE"
    }
  ],
  "queue": [],
  "updatedAt": "2026-07-12T07:20:58.152Z"
}
