{
  "schemaVersion": 1,
  "lock": "wallstop-organization-builds",
  "holder": {
    "holderId": "Ambiguous-Interactive/DxMessaging:28262761057:unity-tests:2022.3.45f1-playmode",
    "repository": "Ambiguous-Interactive/DxMessaging",
    "workflow": "Unity Tests",
    "job": "unity-tests",
    "runId": "28262761057",
    "runAttempt": "1",
    "runUrl": "https://github.com/Ambiguous-Interactive/DxMessaging/actions/runs/28262761057",
    "queuedAt": "2026-06-26T21:21:52.896Z",
    "acquiredAt": "2026-06-26T21:31:13.555Z",
    "expiresAt": "2026-06-27T01:31:13.555Z"
  },
  "queue": [],
  "updatedAt": "2026-06-26T21:31:13.556Z"
}
