{
  "schemaVersion": 5,
  "lock": "wallstop-organization-builds",
  "holder": null,
  "holders": [],
  "queue": [],
  "reservations": [
    {
      "reservationId": "23a0de45-80c7-4ba6-885e-5fc2ac03d0f5",
      "holderId": "Ambiguous-Interactive/qora-redux:30043266138:unity:qora-EditMode",
      "repository": "Ambiguous-Interactive/qora-redux",
      "workflow": "Unity Tests",
      "job": "unity",
      "runId": "30043266138",
      "runAttempt": "1",
      "runUrl": "https://github.com/Ambiguous-Interactive/qora-redux/actions/runs/30043266138",
      "runnerId": "DAD-MACHINE",
      "state": "cooldown",
      "reason": "cleanup-confirmed",
      "createdAt": "2026-07-23T20:51:36.436Z",
      "availableAt": "2026-07-23T20:51:37.436Z"
    }
  ],
  "activeIncident": null,
  "updatedAt": "2026-07-23T20:51:36.436Z"
}
