{
  "schemaVersion": 5,
  "lock": "wallstop-organization-builds",
  "holder": null,
  "holders": [],
  "queue": [],
  "reservations": [
    {
      "reservationId": "0976a0fe-3efe-45a3-97c6-148b795656c4",
      "holderId": "Ambiguous-Interactive/unity-helpers:29380913216:unity-tests-single-threaded:6000.3.16f1-editmode-single-threaded",
      "repository": "Ambiguous-Interactive/unity-helpers",
      "workflow": "Unity Tests",
      "job": "unity-tests-single-threaded",
      "runId": "29380913216",
      "runAttempt": "1",
      "runUrl": "https://github.com/Ambiguous-Interactive/unity-helpers/actions/runs/29380913216",
      "runnerId": "DAD-MACHINE",
      "state": "cooldown",
      "reason": "cleanup-confirmed",
      "createdAt": "2026-07-15T04:29:50.921Z",
      "availableAt": "2026-07-15T04:35:50.921Z"
    }
  ],
  "activeIncident": null,
  "updatedAt": "2026-07-15T04:29:50.921Z"
}
